geo_alchemy/__init__.py
geo_alchemy/exceptions.py
geo_alchemy/geo.py
geo_alchemy/parsers.py
geo_alchemy/utils.py
geo_alchemy/cmd/__init__.py
geo_alchemy/cmd/helpers.py
geo_alchemy/cmd/pp.py
geo_alchemy/cmd/reanno.py
geo_alchemy-0.0.20.dist-info/LICENSE
geo_alchemy-0.0.20.dist-info/METADATA
geo_alchemy-0.0.20.dist-info/WHEEL
geo_alchemy-0.0.20.dist-info/entry_points.txt
geo_alchemy-0.0.20.dist-info/top_level.txt
geo_alchemy-0.0.20.dist-info/RECORD
