Metadata-Version: 2.1
Name: geo-alchemy
Version: 0.0.20
Summary: a Python library and command line tool to make GEO data into gold.
Home-page: https://github.com/soultoolman/geo-alchemy
Author: soultoolman
Author-email: soultooman@gmail.com
License: MIT
Platform: UNKNOWN
Classifier: License :: OSI Approved :: MIT License
Classifier: Programming Language :: Python
Classifier: Programming Language :: Python :: 3
Classifier: Programming Language :: Python :: 3.6
Classifier: Programming Language :: Python :: Implementation :: CPython
Classifier: Programming Language :: Python :: Implementation :: PyPy
Classifier: Topic :: Scientific/Engineering :: Bio-Informatics
Requires-Python: >=3.6.0
Requires-Dist: lxml
Provides-Extra: cmd
Requires-Dist: click ; extra == 'cmd'
Requires-Dist: pandas ; extra == 'cmd'
